{"context":{"time":"1503847284443"},"result":{"1164438":{"context":{},"dscContext":{},"ext":{},"result":[{"_sys_point_local":false,"activity":[{"activityName":"热销手机","bizType":"banner1","id":"187827","imgUrl":"//img.alicdn.com/tfs/TB1isveRXXXXXb3aXXXXXXXXXXX-200-402.jpg","level":"0","lubanUrl":"","targetUrl":"https://www.taobao.com/markets/3c/sj?spm=a21bo.50862.201867-main.13.8laak5"},{"activityName":"淘火炬","bizType":"banner1","id":"187828","imgUrl":"//img.alicdn.com/tfs/TB1nxH0RXXXXXX8XXXXXXXXXXXX-200-402.jpg","level":"0","lubanUrl":"","targetUrl":"https://www.taobao.com/markets/jiadian/index?spm=a21bo.50862.201879-item-1012.4.lJY3Gt"}],"hotwords":[{"id":"181878","level":"0","tag":"","targetUrl":"https://s.taobao.com/search?q=iphone+7&from_type=3c&app=detailproduct","text":"iPhone 7"},{"id":"181879","level":"0","tag":"","targetUrl":"https://s.taobao.com/list?q=s8&style=grid&seller_type=taobao&spm=a219r.lm872.1000187.1&cat=&sort=sale-desc","text":"S8"},{"id":"181880","level":"0","tag":"","targetUrl":"https://s.taobao.com/list?q=%E6%B8%B8%E6%88%8F%E9%BC%A0%E6%A0%87&style=grid&seller_type=taobao&spm=a219r.lm872.1000187.1&cat=","text":"游戏鼠标"},{"id":"181881","level":"0","tag":"","targetUrl":"https://s.taobao.com/list?q=%E6%9C%BA%E6%A2%B0%E9%94%AE%E7%9B%98&style=grid&seller_type=taobao&spm=a219r.lm872.1000187.1&cat=&sort=sale-desc","text":"机械键盘"},{"id":"181882","level":"0","tag":"","targetUrl":"https://s.taobao.com/list?q=%E5%8D%95%E5%8F%8D&cat=11%2C1101%2C1201%2C14%2C1512%2C20%2C50008090%2C50012164%2C50018222%2C50018264%2C50019780%2C50076292&style=grid&seller_type=taobao&spm=a219r.lm872.1000187.1&sort=sale-desc","text":"单反相机"},{"id":"181883","level":"0","tag":"","targetUrl":"https://s.taobao.com/search?q=applewatch&commend=all&ssid=s5-e&search_type=item&sourceId=tb.index&spm=a21bo.50862.201856-taobao-item.1&ie=utf8&initiative_id=tbindexz_20170516&seller_type=taobao&sort=default","text":"AppleWatch"},{"id":"181884","level":"0","tag":"","targetUrl":"https://s.taobao.com/list?q=DIY%E4%B8%BB%E6%9C%BA&style=grid&seller_type=taobao&spm=a219r.lm872.1000187.1&cat=&sort=default","text":"DIY主机"},{"id":"181885","level":"0","tag":"","targetUrl":"https://s.taobao.com/list?&q=智能机器人&seller_type=taobao&osfrom=luoyu","text":"智能机器人"},{"id":"181886","level":"0","tag":"","targetUrl":"https://s.taobao.com/list?&q=制氧机&seller_type=taobao&osfrom=luoyu","text":"制氧机"},{"id":"181887","level":"0","tag":"","targetUrl":"https://s.taobao.com/list?&q=榨汁机&seller_type=taobao&osfrom=luoyu","text":"榨汁机"},{"id":"181888","level":"0","tag":"","targetUrl":"https://s.taobao.com/list?&q=运动耳机&seller_type=taobao&osfrom=luoyu","text":"运动耳机"},{"id":"181889","level":"0","tag":"","targetUrl":"https://s.taobao.com/list?&q=游戏手柄&seller_type=taobao&osfrom=luoyu","text":"游戏手柄"},{"id":"181890","level":"0","tag":"","targetUrl":"https://s.taobao.com/list?&q=饮水机&seller_type=taobao&osfrom=luoyu","text":"饮水机"},{"id":"181891","level":"0","tag":"","targetUrl":"https://s.taobao.com/list?&q=音响&seller_type=taobao&osfrom=luoyu","text":"音响"},{"id":"181892","level":"0","tag":"","targetUrl":"https://s.taobao.com/list?&q=移动硬盘&seller_type=taobao&osfrom=luoyu","text":"移动硬盘"},{"id":"181893","level":"0","tag":"","targetUrl":"https://s.taobao.com/list?&q=一加3&seller_type=taobao&osfrom=luoyu","text":"一加3"},{"id":"181894","level":"0","tag":"","targetUrl":"https://s.taobao.com/list?&q=牙刷&seller_type=taobao&osfrom=luoyu","text":"牙刷"},{"id":"181895","level":"0","tag":"","targetUrl":"https://s.taobao.com/list?&q=宿舍神器&seller_type=taobao&osfrom=luoyu","text":"宿舍神器"},{"id":"181896","level":"0","tag":"","targetUrl":"https://s.taobao.com/list?&q=小米5&seller_type=taobao&osfrom=luoyu","text":"小米5"},{"id":"181897","level":"0","tag":"","targetUrl":"https://s.taobao.com/list?&q=小米&seller_type=taobao&osfrom=luoyu","text":"小米"},{"id":"181898","level":"0","tag":"","targetUrl":"https://s.taobao.com/list?&q=显示器&seller_type=taobao&osfrom=luoyu","text":"显示器"},{"id":"181899","level":"0","tag":"","targetUrl":"https://s.taobao.com/list?&q=吸黑头神器&seller_type=taobao&osfrom=luoyu","text":"吸黑头神器"},{"id":"181900","level":"0","tag":"","targetUrl":"https://s.taobao.com/list?&q=微波炉&seller_type=taobao&osfrom=luoyu","text":"微波炉"},{"id":"181901","level":"0","tag":"","targetUrl":"https://s.taobao.com/list?&q=剃须刀电动&seller_type=taobao&osfrom=luoyu","text":"剃须刀电动"},{"id":"181902","level":"0","tag":"","targetUrl":"https://s.taobao.com/list?&q=剃须刀&seller_type=taobao&osfrom=luoyu","text":"剃须刀"},{"id":"181903","level":"0","tag":"","targetUrl":"https://s.taobao.com/list?&q=体重秤&seller_type=taobao&osfrom=luoyu","text":"体重秤"},{"id":"181904","level":"0","tag":"","targetUrl":"https://s.taobao.com/list?&q=体感游戏&seller_type=taobao&osfrom=luoyu","text":"体感游戏"},{"id":"181905","level":"0","tag":"","targetUrl":"https://s.taobao.com/list?&q=酸奶机&seller_type=taobao&osfrom=luoyu","text":"酸奶机"},{"id":"181906","level":"0","tag":"","targetUrl":"https://s.taobao.com/list?&q=鼠标垫&seller_type=taobao&osfrom=luoyu","text":"鼠标垫"},{"id":"181907","level":"0","tag":"","targetUrl":"https://s.taobao.com/list?&q=鼠标&seller_type=taobao&osfrom=luoyu","text":"鼠标"},{"id":"181908","level":"0","tag":"","targetUrl":"https://s.taobao.com/list?&q=手机支架&seller_type=taobao&osfrom=luoyu","text":"手机支架"},{"id":"181909","level":"0","tag":"","targetUrl":"https://s.taobao.com/list?&q=手机壳&seller_type=taobao&osfrom=luoyu","text":"手机壳"},{"id":"181910","level":"0","tag":"","targetUrl":"https://s.taobao.com/list?&q=手机&seller_type=taobao&osfrom=luoyu","text":"手机"},{"id":"181911","level":"0","tag":"","targetUrl":"https://s.taobao.com/list?&q=手表&seller_type=taobao&osfrom=luoyu","text":"手表"},{"id":"181912","level":"0","tag":"","targetUrl":"https://s.taobao.com/list?&q=扫地机器人&seller_type=taobao&osfrom=luoyu","text":"扫地机器人"},{"id":"181913","level":"0","tag":"","targetUrl":"https://s.taobao.com/list?&q=三星s7&seller_type=taobao&osfrom=luoyu","text":"三星s7"},{"id":"181914","level":"0","tag":"","targetUrl":"https://s.taobao.com/list?&q=三星&seller_type=taobao&osfrom=luoyu","text":"三星"},{"id":"181915","level":"0","tag":"","targetUrl":"https://s.taobao.com/list?&q=荣耀8&seller_type=taobao&osfrom=luoyu","text":"荣耀8"},{"id":"181916","level":"0","tag":"","targetUrl":"https://s.taobao.com/list?&q=去甲醛净化器&seller_type=taobao&osfrom=luoyu","text":"去甲醛净化器"},{"id":"181917","level":"0","tag":"","targetUrl":"https://s.taobao.com/list?&q=苹果6手机壳&seller_type=taobao&osfrom=luoyu","text":"苹果6手机壳"},{"id":"181918","level":"0","tag":"","targetUrl":"https://s.taobao.com/list?&q=苹果6plus手机壳&seller_type=taobao&osfrom=luoyu","text":"苹果6plus手机壳"},{"id":"181919","level":"0","tag":"","targetUrl":"https://s.taobao.com/list?&q=苹果6&seller_type=taobao&osfrom=luoyu","text":"苹果6"},{"id":"181920","level":"0","tag":"","targetUrl":"https://s.taobao.com/list?&q=苹果&seller_type=taobao&osfrom=luoyu","text":"苹果"},{"id":"181921","level":"0","tag":"","targetUrl":"https://s.taobao.com/list?&q=平衡车&seller_type=taobao&osfrom=luoyu","text":"平衡车"},{"id":"181922","level":"0","tag":"","targetUrl":"https://s.taobao.com/list?&q=平板电脑&seller_type=taobao&osfrom=luoyu","text":"平板电脑"},{"id":"181923","level":"0","tag":"","targetUrl":"https://s.taobao.com/list?&q=拍立得&seller_type=taobao&osfrom=luoyu","text":"拍立得"},{"id":"181924","level":"0","tag":"","targetUrl":"https://s.taobao.com/list?&q=内存卡&seller_type=taobao&osfrom=luoyu","text":"内存卡"},{"id":"181925","level":"0","tag":"","targetUrl":"https://s.taobao.com/list?&q=魅族&seller_type=taobao&osfrom=luoyu","text":"魅族"},{"id":"181926","level":"0","tag":"","targetUrl":"https://s.taobao.com/list?&q=美颜相机&seller_type=taobao&osfrom=luoyu","text":"美颜相机"},{"id":"181927","level":"0","tag":"","targetUrl":"https://s.taobao.com/list?&q=美图手机&seller_type=taobao&osfrom=luoyu","text":"美图手机"},{"id":"181928","level":"0","tag":"","targetUrl":"https://s.taobao.com/list?&q=乐视手机&seller_type=taobao&osfrom=luoyu","text":"乐视手机"},{"id":"181929","level":"0","tag":"","targetUrl":"https://s.taobao.com/list?&q=乐视&seller_type=taobao&osfrom=luoyu","text":"乐视"},{"id":"181930","level":"0","tag":"","targetUrl":"https://s.taobao.com/list?&q=老年手机&seller_type=taobao&osfrom=luoyu","text":"老年手机"},{"id":"181931","level":"0","tag":"","targetUrl":"https://s.taobao.com/list?&q=蓝牙音箱&seller_type=taobao&osfrom=luoyu","text":"蓝牙音箱"},{"id":"181932","level":"0","tag":"","targetUrl":"https://s.taobao.com/list?&q=蓝牙耳机&seller_type=taobao&osfrom=luoyu","text":"蓝牙耳机"},{"id":"181933","level":"0","tag":"","targetUrl":"https://s.taobao.com/list?&q=空调扇&seller_type=taobao&osfrom=luoyu","text":"空调扇"},{"id":"181934","level":"0","tag":"","targetUrl":"https://s.taobao.com/list?&q=空调&seller_type=taobao&osfrom=luoyu","text":"空调"},{"id":"181935","level":"0","tag":"","targetUrl":"https://s.taobao.com/list?&q=空气加湿器&seller_type=taobao&osfrom=luoyu","text":"空气加湿器"},{"id":"181936","level":"0","tag":"","targetUrl":"https://s.taobao.com/list?&q=可爱充电宝&seller_type=taobao&osfrom=luoyu","text":"可爱充电宝"},{"id":"181937","level":"0","tag":"","targetUrl":"https://s.taobao.com/list?&q=烤箱家用&seller_type=taobao&osfrom=luoyu","text":"烤箱家用"},{"id":"181938","level":"0","tag":"","targetUrl":"https://s.taobao.com/list?&q=烤箱&seller_type=taobao&osfrom=luoyu","text":"烤箱"},{"id":"181939","level":"0","tag":"","targetUrl":"https://s.taobao.com/list?&q=卷发棒&seller_type=taobao&osfrom=luoyu","text":"卷发棒"},{"id":"181940","level":"0","tag":"","targetUrl":"https://s.taobao.com/list?&q=净水器&seller_type=taobao&osfrom=luoyu","text":"净水器"},{"id":"181941","level":"0","tag":"","targetUrl":"https://s.taobao.com/list?&q=键盘&seller_type=taobao&osfrom=luoyu","text":"键盘"},{"id":"181942","level":"0","tag":"","targetUrl":"https://s.taobao.com/list?&q=家用制氧机&seller_type=taobao&osfrom=luoyu","text":"家用制氧机"},{"id":"181943","level":"0","tag":"","targetUrl":"https://s.taobao.com/list?&q=机械键盘&seller_type=taobao&osfrom=luoyu","text":"机械键盘"},{"id":"181944","level":"0","tag":"","targetUrl":"https://s.taobao.com/list?&q=华为手机&seller_type=taobao&osfrom=luoyu","text":"华为手机"},{"id":"181945","level":"0","tag":"","targetUrl":"https://s.taobao.com/list?&q=华为&seller_type=taobao&osfrom=luoyu","text":"华为"},{"id":"181946","level":"0","tag":"","targetUrl":"https://s.taobao.com/list?&q=固态硬盘&seller_type=taobao&osfrom=luoyu","text":"固态硬盘"},{"id":"181947","level":"0","tag":"","targetUrl":"https://s.taobao.com/list?&q=钢化膜&seller_type=taobao&osfrom=luoyu","text":"钢化膜"},{"id":"181948","level":"0","tag":"","targetUrl":"https://s.taobao.com/list?&q=飞机杯&seller_type=taobao&osfrom=luoyu","text":"飞机杯"},{"id":"181949","level":"0","tag":"","targetUrl":"https://s.taobao.com/list?&q=饭盒&seller_type=taobao&osfrom=luoyu","text":"饭盒"},{"id":"181950","level":"0","tag":"","targetUrl":"https://s.taobao.com/list?&q=耳机入耳式&seller_type=taobao&osfrom=luoyu","text":"耳机入耳式"},{"id":"181951","level":"0","tag":"","targetUrl":"https://s.taobao.com/list?&q=耳机&seller_type=taobao&osfrom=luoyu","text":"耳机"},{"id":"181952","level":"0","tag":"","targetUrl":"https://s.taobao.com/list?&q=儿童手表&seller_type=taobao&osfrom=luoyu","text":"儿童手表"},{"id":"181953","level":"0","tag":"","targetUrl":"https://s.taobao.com/list?&q=豆浆机&seller_type=taobao&osfrom=luoyu","text":"豆浆机"},{"id":"181954","level":"0","tag":"","targetUrl":"https://s.taobao.com/list?&q=电子书&seller_type=taobao&osfrom=luoyu","text":"电子书"},{"id":"181955","level":"0","tag":"","targetUrl":"https://s.taobao.com/list?&q=电子称&seller_type=taobao&osfrom=luoyu","text":"电子称"},{"id":"181956","level":"0","tag":"","targetUrl":"https://s.taobao.com/list?&q=电热水壶&seller_type=taobao&osfrom=luoyu","text":"电热水壶"},{"id":"181957","level":"0","tag":"","targetUrl":"https://s.taobao.com/list?&q=电脑主机&seller_type=taobao&osfrom=luoyu","text":"电脑主机"},{"id":"181958","level":"0","tag":"","targetUrl":"https://s.taobao.com/list?&q=电火锅&seller_type=taobao&osfrom=luoyu","text":"电火锅"},{"id":"181959","level":"0","tag":"","targetUrl":"https://s.taobao.com/list?&q=电风扇&seller_type=taobao&osfrom=luoyu","text":"电风扇"},{"id":"181960","level":"0","tag":"","targetUrl":"https://s.taobao.com/list?&q=电饭煲&seller_type=taobao&osfrom=luoyu","text":"电饭煲"},{"id":"181961","level":"0","tag":"","targetUrl":"https://s.taobao.com/list?&q=电动牙刷&seller_type=taobao&osfrom=luoyu","text":"电动牙刷"},{"id":"181962","level":"0","tag":"","targetUrl":"https://s.taobao.com/list?&q=电磁炉&seller_type=taobao&osfrom=luoyu","text":"电磁炉"},{"id":"181963","level":"0","tag":"","targetUrl":"https://s.taobao.com/list?&q=吹风机&seller_type=taobao&osfrom=luoyu","text":"吹风机"},{"id":"181964","level":"0","tag":"","targetUrl":"https://s.taobao.com/list?&q=充电宝&seller_type=taobao&osfrom=luoyu","text":"充电宝"},{"id":"181965","level":"0","tag":"","targetUrl":"https://s.taobao.com/list?&q=车载手机支架&seller_type=taobao&osfrom=luoyu","text":"车载手机支架"},{"id":"181966","level":"0","tag":"","targetUrl":"https://s.taobao.com/list?&q=车载充电器&seller_type=taobao&osfrom=luoyu","text":"车载充电器"},{"id":"181967","level":"0","tag":"","targetUrl":"https://s.taobao.com/list?&q=笔记本&seller_type=taobao&osfrom=luoyu","text":"笔记本"},{"id":"181968","level":"0","tag":"","targetUrl":"https://s.taobao.com/list?&q=按摩器&seller_type=taobao&osfrom=luoyu","text":"按摩器"},{"id":"181969","level":"0","tag":"","targetUrl":"https://s.taobao.com/list?&q=vsco滤镜 全滤镜&seller_type=taobao&osfrom=luoyu","text":"vsco滤镜 全滤镜"},{"id":"181970","level":"0","tag":"","targetUrl":"https://s.taobao.com/list?&q=VR眼镜&seller_type=taobao&osfrom=luoyu","text":"VR眼镜"},{"id":"181971","level":"0","tag":"","targetUrl":"https://s.taobao.com/list?&q=vivo&seller_type=taobao&osfrom=luoyu","text":"vivo"},{"id":"181972","level":"0","tag":"","targetUrl":"https://s.taobao.com/list?&q=u盘&seller_type=taobao&osfrom=luoyu","text":"u盘"},{"id":"181973","level":"0","tag":"","targetUrl":"https://s.taobao.com/list?&q=oppo&seller_type=taobao&osfrom=luoyu","text":"oppo"},{"id":"181974","level":"0","tag":"","targetUrl":"https://s.taobao.com/list?&q=mp3&seller_type=taobao&osfrom=luoyu","text":"mp3"},{"id":"181975","level":"0","tag":"","targetUrl":"https://s.taobao.com/list?&q=iphone6&seller_type=taobao&osfrom=luoyu","text":"iphone6"},{"id":"181976","level":"0","tag":"","targetUrl":"https://s.taobao.com/list?&q=ipad&seller_type=taobao&osfrom=luoyu","text":"ipad"},{"id":"181977","level":"0","tag":"","targetUrl":"https://s.taobao.com/list?&q=3D打印机&seller_type=taobao&osfrom=luoyu","text":"3D打印机"},{"id":"181978","level":"0","tag":"","targetUrl":"https://s.taobao.com/list?&q=智能电子秤&seller_type=taobao&osfrom=luoyu","text":"智能电子秤"}],"item":[{"bizType":"item2","enablePersonal":"y","id":"182822","imgUrl":"//img.alicdn.com/tfs/TB1kubWQVXXXXXlapXXXXXXXXXX-200-200.jpg","level":"0","targetUrl":"https://www.taobao.com/markets/3c/shuma?spm=a21bo.50862.201867-main.12.8laak5","text1":"数码好货","text2":"等你来看"},{"bizType":"item2","enablePersonal":"","id":"182823","imgUrl":"//img.alicdn.com/tfs/TB1TUv0QVXXXXb9aXXXXXXXXXXX-200-200.jpg","level":"0","targetUrl":"https://www.taobao.com/markets/jiadian/index?spm=a217h.8239130.305603.13.5hSAqQ","text1":"品质家电","text2":"生活新选"}],"news":[{"bizType":"news3","id":"187824","imgUrl":"//img.alicdn.com/tfs/TB1Ya3aQVXXXXa3XVXXXXXXXXXX-360-280.jpg","level":"0","targetUrl":"https://www.taobao.com/markets/3c/shuma?spm=a21bo.50862.201879-item-1012.3.lJY3Gt","text1":"数码","text2":"品质好货优选","text3":"为你精选数码行业优质好货"},{"bizType":"news2","id":"187825","imgUrl":"//img.alicdn.com/tfs/TB1lSfgRXXXXXXLapXXXXXXXXXX-240-130.jpg","level":"0","targetUrl":"https://www.taobao.com/markets/3c/2s?spm=a217h.8161588.305603.13.TXveR4","text1":"二手数码商品","text2":"","text3":""},{"bizType":"news2","id":"187826","imgUrl":"//img.alicdn.com/tfs/TB1iVD3RXXXXXapXXXXXXXXXXXX-240-130.jpg","level":"0","targetUrl":"https://www.taobao.com/markets/3c/taodianlianmeng?wh_ttid=pc","text1":"区域零售速达","text2":"","text3":""}],"totalinfo":[{"bizCode":"caodianjie","bizName":"潮电街","cna":"Pg8rEf0gvzcCAXkAHd0hvIRt","debugInfo":"lubanclose,key:falsellat","id":"6033","imgUrl":"//gtms04.alicdn.com/tps/i4/TB1JaLCLVXXXXcPaXXX07tlTXXX-200-200.png","level":"0","logoBackgroundColor":"#406cc0","name":"潮电街","productId":"1012","scm":"","targetUrl":"http://www.taobao.com/markets/cdj/index","templateId":"t3","textBackgroundColor":"#459ac4","topOrder":"","userId":"0"}]},{"_sys_point_local":false,"activity":[{"activityName":"极有家·挑颜值","bizType":"banner1","id":"196338","imgUrl":"//img.alicdn.com/tfs/TB1Q79kSVXXXXbvXFXXXXXXXXXX-200-402.jpg","level":"0","lubanUrl":"","targetUrl":"https://www.taobao.com/markets/youjia/zaoshenghuotiaoyanzhi12"},{"activityName":"每周话题日常","bizType":"banner1","id":"196339","imgUrl":"//img.alicdn.com/tfs/TB1.XiuSVXXXXazaXXXXXXXXXXX-200-402.jpg","level":"0","lubanUrl":"","targetUrl":"https://www.taobao.com/markets/youjia/huatipc_copy"}],"hotwords":[{"id":"123403","level":"0","tag":"hot","targetUrl":"https://s.taobao.com/list?source=youjia&q=%E6%B5%B4%E5%AE%A4%E6%9F%9C","text":"浴室柜"},{"id":"123404","level":"0","tag":"","targetUrl":"https://s.taobao.com/list?source=youjia&q=%E7%93%B7%E7%A0%96","text":"瓷砖"},{"id":"123405","level":"0","tag":"","targetUrl":"https://s.taobao.com/list?source=youjia&q=%E7%81%AF","text":"美灯"},{"id":"123406","level":"0","tag":"","targetUrl":"https://s.taobao.com/list?source=youjia&q=%E5%A2%99%E7%BA%B8","text":"墙纸"},{"id":"123407","level":"0","tag":"","targetUrl":"https://s.taobao.com/list?source=youjia&q=%E5%9C%B0%E6%9D%BF","text":"地板"},{"id":"123408","level":"0","tag":"","targetUrl":"https://s.taobao.com/list?source=youjia&q=%E5%90%8A%E9%A1%B6","text":"吊顶"},{"id":"123409","level":"0","tag":"","targetUrl":"https://s.taobao.com/list?spm=5704.7773518.226594.66.0EDXMH&source=youjia&cat=56590032","text":"装修"},{"id":"123410","level":"0","tag":"","targetUrl":"https://s.taobao.com/list?spm=5704.7773518.226594.66.0EDXMH&source=youjia&cat=56590032","text":"样板"},{"id":"123411","level":"0","tag":"hot","targetUrl":"http://s.taobao.com/list?source=youjia&q=%E5%BA%8A","text":"床"},{"id":"123412","level":"0","tag":"hot","targetUrl":"http://s.taobao.com/list?source=youjia&q=%E6%94%B6%E7%BA%B3%E7%AE%B1","text":"收纳"},{"id":"123413","level":"0","tag":"","targetUrl":"http://s.taobao.com/list?source=youjia&q=%E5%85%A8%E6%A3%89%E5%9B%9B%E4%BB%B6%E5%A5%97","text":"四件套"},{"id":"123414","level":"0","tag":"","targetUrl":"http://s.taobao.com/list?source=youjia&q=%E9%A4%90%E5%85%B7%E5%A5%97%E8%A3%85","text":"餐具"},{"id":"123415","level":"0","tag":"","targetUrl":"https://s.taobao.com/list?spm=5704.7773518.226594.34.BsB7L4&source=youjia&q=%E5%86%AC%E8%A2%AB&cat=50010825&cps=yes&ppath=6861561%3A28349","text":"冬被"},{"id":"123416","level":"0","tag":"","targetUrl":"https://s.taobao.com/list?spm=5704.7773518.226594.37.BsB7L4&source=youjia&q=%E6%AF%9B%E6%AF%AF&cat=50001871","text":"毛毯"},{"id":"123417","level":"0","tag":"","targetUrl":"http://s.taobao.com/list?source=youjia&q=%E8%AE%BE%E8%AE%A1%E5%AE%B6%E5%85%B7","text":"家具"},{"id":"123418","level":"0","tag":"hot","targetUrl":"http://s.taobao.com/list?source=youjia&q=%E6%B2%99%E5%8F%91","text":"沙发"},{"id":"123419","level":"0","tag":"","targetUrl":"https://s.taobao.com/list?spm=a21bo.50862.201867-links-11.8.lKUgux&source=youjia&q=%E8%8C%B6%E5%87%A0","text":"茶几"},{"id":"123420","level":"0","tag":"","targetUrl":"https://www.taobao.com/markets/youjia/optimizationdesign","text":"全套设计"}],"item":[{"bizType":"item2","enablePersonal":"","id":"196346","imgUrl":"//img.alicdn.com/tfs/TB17tOMSVXXXXbUXFXXXXXXXXXX-400-400.jpg","level":"0","targetUrl":"https://www.taobao.com/markets/youjia/marketskantugou2","text1":"榻榻米","text2":"搭在一起"},{"bizType":"item2","enablePersonal":"","id":"196347","imgUrl":"//img.alicdn.com/tps/TB1qoCENVXXXXbZXFXXXXXXXXXX-200-200.jpg","level":"0","targetUrl":"https://youjia.taobao.com/n/construction/index?spm=a21bo.50862.201879-item-1005-links.8&pvid=687f12d1-052b-493e-8b60-28d9176e295","text1":"装修预约","text2":"量房设计"}],"news":[{"bizType":"news3","id":"196215","imgUrl":"//img.alicdn.com/tfs/TB1TYA7QVXXXXcMapXXXXXXXXXX-360-280.jpg","level":"0","targetUrl":"https://www.taobao.com/markets/youjia/jiyoujiaqiangxin","text1":"抢新鲜","text2":"夏日换季好货选","text3":"每天为你挑选当天上新的优选商品，更有低至五折的优惠价格。"},{"bizType":"news2","id":"196216","imgUrl":"//img.alicdn.com/tfs/TB1olf9SFXXXXX8aXXXXXXXXXXX-240-130.jpg","level":"0","targetUrl":"https://riji.taobao.com/yjriji/diarylist.htm?spm=a21bo.50862.201879-item-1005.7.DtZxSL","text1":"IT男精打细算","text2":"","text3":""},{"bizType":"news2","id":"196217","imgUrl":"//img.alicdn.com/tfs/TB15dBUSFXXXXa6aXXXXXXXXXXX-240-130.jpg","level":"0","targetUrl":"http://youjia.taobao.com/n/pictures/list?spm=a1z52.7915890.0.0.yhPptb&isLingan=false","text1":"最爱简约美式","text2":"","text3":""}],"totalinfo":[{"bizCode":"jiyoujia","bizName":"极有家","id":"5849","imgUrl":"//img.alicdn.com/tps/TB1yJjPLVXXXXbhXFXXXXXXXXXX-200-200.png","level":"0","logoBackgroundColor":"#e9a326","name":"极有家","productId":"1005","scm":"","targetUrl":"http://www.jiyoujia.com/","templateId":"t3","textBackgroundColor":"#e9a326","topOrder":"1","userId":"0"}]},{"_sys_point_local":false,"activity":[{"activityName":"","bizType":"banner1","id":"141030","imgUrl":"//img.alicdn.com/tps/TB13Ae5OpXXXXa6XFXXXXXXXXXX-200-402.jpg","level":"0","lubanUrl":"","targetUrl":"https://www.taobao.com/markets/quality/v2/srp?q=%E6%94%B6%E7%BA%B3&source=zhizao&at=71490&no_mini_doufu=true&spu_hit=off&spm=a21c0.8071293.search.dsearch#!pSize=60&json=on&_input_charset=utf-8&spm=a21c0.8071293.search.dsearch&q=%E6%94%B6%E7%BA%B3&source=zhizao&at=71490&no_mini_doufu=true&spu_hit=off"},{"activityName":"","bizType":"banner2","id":"141031","imgUrl":"//img.alicdn.com/tps/TB1jjaYOFXXXXa2aXXXXXXXXXXX-276-402.jpg","level":"0","lubanUrl":"","targetUrl":"https://www.taobao.com/markets/quality/pingce-detail?spm=a21c0.8077664.349443.1.0by3hC&feedId=200135565412"}],"hotwords":[{"id":"177266","level":"0","tag":"hot","targetUrl":"https://s.taobao.com/list?q=%E8%BF%9E%E8%A1%A3%E8%A3%99&source=zhizao&auction_tag%5B%5D=71490&no_mini_doufu=true&spu_hit=off&spm=a21c0.8071293.search.dsearch","text":"连衣裙"},{"id":"177267","level":"0","tag":"","targetUrl":"https://s.taobao.com/list?q=%E5%8D%95%E9%9E%8B&source=zhizao&auction_tag%5B%5D=71490&no_mini_doufu=true&spu_hit=off&spm=a21c0.7788802.search.dsearch","text":"单鞋"},{"id":"177268","level":"0","tag":"","targetUrl":"https://s.taobao.com/list?q=%E6%B2%99%E5%8F%91&source=zhizao&auction_tag%5B%5D=71490&no_mini_doufu=true&spu_hit=off&spm=a21c0.7788802.search.dsearch","text":"沙发"},{"id":"177269","level":"0","tag":"","targetUrl":"https://s.taobao.com/list?q=%E7%9C%9F%E7%9A%AE%E5%A5%B3%E5%8C%85&source=zhizao&auction_tag%5B%5D=71490&no_mini_doufu=true&spu_hit=off&spm=a21c0.8071293.search.dsearch","text":"真皮女包"},{"id":"177270","level":"0","tag":"","targetUrl":"https://s.taobao.com/list?q=%E9%A3%8E%E8%A1%A3&source=zhizao&auction_tag%5B%5D=71490&no_mini_doufu=true&spu_hit=off&spm=a21c0.8071293.search.dsearch","text":"风衣"},{"id":"177271","level":"0","tag":"","targetUrl":"https://s.taobao.com/list?q=%E6%8C%89%E6%91%A9%E9%9D%A0%E5%9E%AB&source=zhizao&auction_tag%5B%5D=71490&no_mini_doufu=true&spu_hit=off&spm=a21c0.8071293.search.dsearch","text":"按摩靠垫"},{"id":"177272","level":"0","tag":"","targetUrl":"https://s.taobao.com/list?q=%E8%BF%90%E5%8A%A8%E6%9C%8D&source=zhizao&auction_tag%5B%5D=71490&no_mini_doufu=true&spu_hit=off&spm=a21c0.8071293.search.dsearch","text":"运动服"},{"id":"177273","level":"0","tag":"","targetUrl":"https://s.taobao.com/list?q=%E5%9B%9B%E4%BB%B6%E5%A5%97&source=zhizao&auction_tag%5B%5D=71490&no_mini_doufu=true&spu_hit=off&spm=a21c0.8071293.search.dsearch","text":"四件套"},{"id":"177274","level":"0","tag":"hot","targetUrl":"https://s.taobao.com/list?q=%E8%A1%8C%E6%9D%8E%E7%AE%B1&source=zhizao&auction_tag%5B%5D=71490&no_mini_doufu=true&spu_hit=off&spm=a21c0.8071293.search.dsearch","text":"行李箱"},{"id":"177275","level":"0","tag":"","targetUrl":"https://s.taobao.com/list?q=%E7%94%B7%E5%A3%AB%E8%A1%AC%E8%A1%AB&source=zhizao&auction_tag%5B%5D=71490&no_mini_doufu=true&spu_hit=off&spm=a21c0.8071293.search.dsearch","text":"牛仔裤"},{"id":"177276","level":"0","tag":"","targetUrl":"https://s.taobao.com/list?q=%E7%94%B5%E6%B0%B4%E5%A3%B6&source=zhizao&auction_tag%5B%5D=71490&no_mini_doufu=true&spu_hit=off&spm=a21c0.8071293.search.dsearch","text":"电水壶"},{"id":"177277","level":"0","tag":"","targetUrl":"https://s.taobao.com/list?q=%E7%94%B5%E9%A5%AD%E7%85%B2&source=zhizao&auction_tag%5B%5D=71490&no_mini_doufu=true&spu_hit=off&spm=a21c0.8071293.search.dsearch","text":"电饭煲"}],"item":[{"bizType":"item1","enablePersonal":"y","id":"73864","imgUrl":"https://img.alicdn.com/tps/TB1wxzHLVXXXXboXVXXXXXXXXXX-80-80.jpg","level":"0","targetUrl":"http://q.taobao.com","text1":"品质优选","text2":""},{"bizType":"item1","enablePersonal":"y","id":"73865","imgUrl":"https://img.alicdn.com/tps/TB1d_vBLVXXXXbqaXXXXXXXXXXX-80-80.jpg","level":"0","targetUrl":"http://q.taobao.com","text1":"大厂直供","text2":""},{"bizType":"item2","enablePersonal":"y","id":"73866","imgUrl":"https://img.alicdn.com/tps/TB1FbnzLVXXXXXEapXXXXXXXXXX-60-60.jpg","level":"0","targetUrl":"http://q.taobao.com","text1":"国货精品","text2":"质造首选"},{"bizType":"item2","enablePersonal":"y","id":"73867","imgUrl":"https://img.alicdn.com/tps/TB1OmvBLVXXXXbbaXXXXXXXXXXX-60-60.jpg","level":"0","targetUrl":"http://q.taobao.com","text1":"猜你喜欢","text2":"好货不贵"}],"news":[{"bizType":"news1","id":"177285","imgUrl":"//img.alicdn.com/tps/TB1G8HpOFXXXXb.apXXXXXXXXXX-360-280.jpg","level":"0","targetUrl":"https://s.taobao.com/list?q=%E5%B0%8F%E5%AE%B6%E5%85%B7&source=zhizao&auction_tag%5B%5D=71490&no_mini_doufu=true&spu_hit=off&spm=a21c0.8071293.search.dsearch","text1":"好货不贵","text2":"小户型家具这样选","text3":""}],"totalinfo":[{"bizCode":"zhongguozhizao","bizName":"中国质造","id":"6029","imgUrl":"//gw.alicdn.com/tps/TB1JBxFLpXXXXcNXpXXXXXXXXXX-200-200.png","level":"0","logoBackgroundColor":"#e44346","name":"中国质造","productId":"1007","scm":"","targetUrl":"http://q.taobao.com","templateId":"t1","textBackgroundColor":"#f45258","topOrder":"","userId":"0"}]},{"_sys_point_local":false,"activity":[{"activityName":"banner1","bizType":"banner1","id":"185777","imgUrl":"//img.alicdn.com/tfs/TB1mrvPRFXXXXX2XFXXXXXXXXXX-200-402.jpg","level":"0","lubanUrl":"","targetUrl":"https://guang.taobao.com/activity/channel.htm?id=713"},{"activityName":"banner2","bizType":"banner2","id":"185778","imgUrl":"//img.alicdn.com/tfs/TB11zzRQVXXXXXvaXXXXXXXXXXX-276-402.jpg","level":"0","lubanUrl":"","targetUrl":"https://guang.taobao.com/activity/channel.htm?id=582"}],"hotwords":[{"id":"185822","level":"0","tag":"hot","targetUrl":"https://guang.taobao.com/street/fushi.htm?catId=1&tagId=11407","text":"T恤"},{"id":"185823","level":"0","tag":"","targetUrl":"https://guang.taobao.com/street/fushi.htm?catId=1&tagId=11411","text":"衬衫"},{"id":"185824","level":"0","tag":"hot","targetUrl":"https://guang.taobao.com/street/fushi.htm?catId=1&tagId=12109","text":"连衣裙"},{"id":"185825","level":"0","tag":"","targetUrl":"https://guang.taobao.com/street/fushi.htm?catId=1&tagId=11769","text":"雪纺衫"},{"id":"185826","level":"0","tag":"hot","targetUrl":"https://guang.taobao.com/street/fushi.htm?catId=3&tagId=12089","text":"凉鞋"},{"id":"185827","level":"0","tag":"hot","targetUrl":"https://guang.taobao.com/street/fushi.htm?catId=1&tagId=12041","text":"东大门"},{"id":"185828","level":"0","tag":"","targetUrl":"https://guang.taobao.com/street/meizhuang.htm?catId=7&tagId=11346","text":"画眼妆"},{"id":"185829","level":"0","tag":"hot","targetUrl":"https://guang.taobao.com/street/meizhuang.htm?catId=21&tagId=11328","text":"学扎发"},{"id":"185830","level":"0","tag":"","targetUrl":"https://guang.taobao.com/street/fushi.htm?catId=4&tagId=11242","text":"单肩包"},{"id":"185831","level":"0","tag":"","targetUrl":"https://guang.taobao.com/street/jiaju.htm?catId=6&tagId=12430","text":"沙发"},{"id":"185832","level":"0","tag":"","targetUrl":"https://guang.taobao.com/street/fushi.htm?catId=3&tagId=12086","text":"单鞋"},{"id":"185833","level":"0","tag":"","targetUrl":"https://guang.taobao.com/street/jiaju.htm?catId=6&tagId=12470","text":"多肉"},{"id":"185834","level":"0","tag":"","targetUrl":"https://guang.taobao.com/street/fushi.htm?catId=1&tagId=11850","text":"风衣"},{"id":"185835","level":"0","tag":"","targetUrl":"https://guang.taobao.com/street/fushi.htm?catId=1&tagId=11873","text":"毛衣"},{"id":"185836","level":"0","tag":"","targetUrl":"https://guang.taobao.com/street/fushi.htm?catId=1&tagId=11855","text":"卫衣"},{"id":"185837","level":"0","tag":"","targetUrl":"https://guang.taobao.com/street/fushi.htm?catId=1&tagId=12102","text":"开衫"},{"id":"185838","level":"0","tag":"","targetUrl":"https://guang.taobao.com/street/fushi.htm?catId=1&tagId=11417","text":"小西装"},{"id":"185839","level":"0","tag":"","targetUrl":"https://guang.taobao.com/street/fushi.htm?catId=1&tagId=12036","text":"罩衫"},{"id":"185840","level":"0","tag":"","targetUrl":"https://guang.taobao.com/street/fushi.htm?catId=1&tagId=11874","text":"马甲"},{"id":"185841","level":"0","tag":"","targetUrl":"https://guang.taobao.com/street/fushi.htm?catId=1&tagId=12195","text":"短外套"},{"id":"185842","level":"0","tag":"","targetUrl":"https://guang.taobao.com/street/fushi.htm?catId=1&tagId=11415","text":"针织衫"},{"id":"185843","level":"0","tag":"","targetUrl":"https://guang.taobao.com/street/fushi.htm?catId=1&tagId=12005","text":"防晒衫"},{"id":"185844","level":"0","tag":"","targetUrl":"https://guang.taobao.com/street/fushi.htm?catId=1&tagId=11915","text":"棉服"},{"id":"185845","level":"0","tag":"","targetUrl":"https://guang.taobao.com/street/fushi.htm?catId=1&tagId=11910","text":"羽绒服"},{"id":"185846","level":"0","tag":"","targetUrl":"https://guang.taobao.com/street/fushi.htm?catId=1&tagId=11869","text":"呢大衣"},{"id":"185847","level":"0","tag":"","targetUrl":"https://guang.taobao.com/street/fushi.htm?catId=1&tagId=12114","text":"斗篷"},{"id":"185848","level":"0","tag":"","targetUrl":"https://guang.taobao.com/street/fushi.htm?catId=1&tagId=11204","text":"半身裙"},{"id":"185849","level":"0","tag":"","targetUrl":"https://guang.taobao.com/street/fushi.htm?catId=1&tagId=11376","text":"短裙"},{"id":"185850","level":"0","tag":"","targetUrl":"https://guang.taobao.com/street/fushi.htm?catId=1&tagId=11787","text":"长裙"},{"id":"185851","level":"0","tag":"","targetUrl":"https://guang.taobao.com/street/fushi.htm?catId=1&tagId=12038","text":"包臀裙"},{"id":"185852","level":"0","tag":"","targetUrl":"https://guang.taobao.com/street/fushi.htm?catId=1&tagId=12040","text":"牛仔裙"},{"id":"185853","level":"0","tag":"","targetUrl":"https://guang.taobao.com/street/fushi.htm?catId=1&tagId=12049","text":"背带裙"},{"id":"185854","level":"0","tag":"","targetUrl":"https://guang.taobao.com/street/fushi.htm?catId=1&tagId=12006","text":"沙滩裙"},{"id":"185855","level":"0","tag":"","targetUrl":"https://guang.taobao.com/street/fushi.htm?catId=1&tagId=12365","text":"网纱裙"},{"id":"185856","level":"0","tag":"","targetUrl":"https://guang.taobao.com/street/fushi.htm?catId=1&tagId=11404","text":"牛仔裤"},{"id":"185857","level":"0","tag":"","targetUrl":"https://guang.taobao.com/street/fushi.htm?catId=1&tagId=11382","text":"哈伦裤"},{"id":"185858","level":"0","tag":"","targetUrl":"https://guang.taobao.com/street/fushi.htm?catId=1&tagId=11397","text":"休闲裤"},{"id":"185859","level":"0","tag":"","targetUrl":"https://guang.taobao.com/street/fushi.htm?catId=1&tagId=12100","text":"铅笔裤"},{"id":"185860","level":"0","tag":"","targetUrl":"https://guang.taobao.com/street/fushi.htm?catId=1&tagId=11380","text":"短裤"},{"id":"185861","level":"0","tag":"","targetUrl":"https://guang.taobao.com/street/fushi.htm?catId=1&tagId=12031","text":"背带裤"},{"id":"185862","level":"0","tag":"","targetUrl":"https://guang.taobao.com/street/fushi.htm?catId=1&tagId=11395","text":"打底裤"},{"id":"185863","level":"0","tag":"","targetUrl":"https://guang.taobao.com/street/fushi.htm?catId=1&tagId=11423","text":"抹胸"},{"id":"185864","level":"0","tag":"","targetUrl":"https://guang.taobao.com/street/fushi.htm?catId=1&tagId=11425","text":"文胸"},{"id":"185865","level":"0","tag":"","targetUrl":"https://guang.taobao.com/street/fushi.htm?catId=1&tagId=11427","text":"内裤"},{"id":"185866","level":"0","tag":"","targetUrl":"https://guang.taobao.com/street/fushi.htm?catId=1&tagId=11429","text":"家居服"},{"id":"185867","level":"0","tag":"","targetUrl":"https://guang.taobao.com/street/fushi.htm?catId=1&tagId=11431","text":"睡衣"},{"id":"185868","level":"0","tag":"","targetUrl":"https://guang.taobao.com/street/fushi.htm?catId=1&tagId=11435","text":"泳衣"},{"id":"185869","level":"0","tag":"","targetUrl":"https://guang.taobao.com/street/fushi.htm?catId=1&tagId=12302","text":"吊带背心"},{"id":"185870","level":"0","tag":"","targetUrl":"https://guang.taobao.com/street/fushi.htm?catId=1&tagId=11967","text":"袜子"},{"id":"185871","level":"0","tag":"","targetUrl":"https://guang.taobao.com/street/fushi.htm?catId=1&tagId=11468","text":"韩范"},{"id":"185872","level":"0","tag":"","targetUrl":"https://guang.taobao.com/street/fushi.htm?catId=1&tagId=11998","text":"欧美风"},{"id":"185873","level":"0","tag":"","targetUrl":"https://guang.taobao.com/street/fushi.htm?catId=1&tagId=11473","text":"日系"},{"id":"185874","level":"0","tag":"","targetUrl":"https://guang.taobao.com/street/fushi.htm?catId=1&tagId=11470","text":"英伦风"},{"id":"185875","level":"0","tag":"","targetUrl":"https://guang.taobao.com/street/fushi.htm?catId=1&tagId=12104","text":"森女风"},{"id":"185876","level":"0","tag":"","targetUrl":"https://guang.taobao.com/street/fushi.htm?catId=1&tagId=12108","text":"通勤"},{"id":"185877","level":"0","tag":"","targetUrl":"https://guang.taobao.com/street/fushi.htm?catId=1&tagId=12037","text":"民族风"},{"id":"185878","level":"0","tag":"","targetUrl":"https://guang.taobao.com/street/fushi.htm?catId=1&tagId=11439","text":"蕾丝"},{"id":"185879","level":"0","tag":"","targetUrl":"https://guang.taobao.com/street/fushi.htm?catId=1&tagId=11443","text":"雪纺"},{"id":"185880","level":"0","tag":"","targetUrl":"https://guang.taobao.com/street/fushi.htm?catId=1&tagId=11880","text":"条纹"},{"id":"185881","level":"0","tag":"","targetUrl":"https://guang.taobao.com/street/fushi.htm?catId=1&tagId=12030","text":"格子"},{"id":"185882","level":"0","tag":"","targetUrl":"https://guang.taobao.com/street/fushi.htm?catId=1&tagId=12097","text":"棉麻"},{"id":"185883","level":"0","tag":"","targetUrl":"https://guang.taobao.com/street/fushi.htm?catId=1&tagId=12004","text":"闪钻"},{"id":"185884","level":"0","tag":"","targetUrl":"https://guang.taobao.com/street/fushi.htm?catId=1&tagId=11453","text":"绣花"},{"id":"185885","level":"0","tag":"","targetUrl":"https://guang.taobao.com/street/fushi.htm?catId=1&tagId=11447","text":"撞色"},{"id":"185886","level":"0","tag":"","targetUrl":"https://guang.taobao.com/street/fushi.htm?catId=1&tagId=11456","text":"铆钉"},{"id":"185887","level":"0","tag":"","targetUrl":"https://guang.taobao.com/street/fushi.htm?catId=3&tagId=11957","text":"尖头鞋"},{"id":"185888","level":"0","tag":"","targetUrl":"https://guang.taobao.com/street/fushi.htm?catId=3&tagId=11996","text":"圆头鞋"},{"id":"185889","level":"0","tag":"","targetUrl":"https://guang.taobao.com/street/fushi.htm?catId=3&tagId=11960","text":"帆布鞋"},{"id":"185890","level":"0","tag":"","targetUrl":"https://guang.taobao.com/street/fushi.htm?catId=3&tagId=12092","text":"高跟鞋"},{"id":"185891","level":"0","tag":"","targetUrl":"https://guang.taobao.com/street/fushi.htm?catId=3&tagId=11951","text":"坡跟鞋"},{"id":"185892","level":"0","tag":"","targetUrl":"https://guang.taobao.com/street/fushi.htm?catId=3&tagId=12086","text":"平底鞋"},{"id":"185893","level":"0","tag":"","targetUrl":"https://guang.taobao.com/street/fushi.htm?catId=3&tagId=11958","text":"高帮鞋"},{"id":"185894","level":"0","tag":"","targetUrl":"https://guang.taobao.com/street/fushi.htm?catId=3&tagId=11659","text":"鱼嘴鞋"},{"id":"185895","level":"0","tag":"","targetUrl":"https://guang.taobao.com/street/fushi.htm?catId=3&tagId=11966","text":"松糕鞋"},{"id":"185896","level":"0","tag":"","targetUrl":"https://guang.taobao.com/street/fushi.htm?catId=3&tagId=11960","text":"帆布鞋"},{"id":"185897","level":"0","tag":"","targetUrl":"https://guang.taobao.com/street/fushi.htm?catId=3&tagId=12086","text":"板鞋"},{"id":"185898","level":"0","tag":"","targetUrl":"https://guang.taobao.com/street/fushi.htm?catId=3&tagId=12112","text":"短靴"},{"id":"185899","level":"0","tag":"","targetUrl":"https://guang.taobao.com/street/fushi.htm?catId=3&tagId=12124","text":"机车靴"},{"id":"185900","level":"0","tag":"","targetUrl":"https://guang.taobao.com/street/fushi.htm?catId=3&tagId=12107","text":"长筒靴"},{"id":"185901","level":"0","tag":"","targetUrl":"https://guang.taobao.com/street/fushi.htm?catId=3&tagId=12105","text":"流苏靴"},{"id":"185902","level":"0","tag":"","targetUrl":"https://guang.taobao.com/street/fushi.htm?catId=3&tagId=11956","text":"雪地靴"},{"id":"185903","level":"0","tag":"","targetUrl":"https://guang.taobao.com/street/fushi.htm?catId=3&tagId=12111","text":"踝靴"},{"id":"185904","level":"0","tag":"","targetUrl":"https://guang.taobao.com/street/fushi.htm?catId=4&tagId=11241","text":"斜挎包"},{"id":"185905","level":"0","tag":"","targetUrl":"https://guang.taobao.com/street/fushi.htm?catId=4&tagId=11243","text":"双肩包"},{"id":"185906","level":"0","tag":"","targetUrl":"https://guang.taobao.com/street/fushi.htm?catId=4&tagId=11928","text":"手拿包"},{"id":"185907","level":"0","tag":"","targetUrl":"https://guang.taobao.com/street/fushi.htm?catId=4&tagId=11929","text":"钱包"},{"id":"185908","level":"0","tag":"","targetUrl":"https://guang.taobao.com/street/fushi.htm?catId=4&tagId=11930","text":"旅行箱"},{"id":"185909","level":"0","tag":"","targetUrl":"https://guang.taobao.com/street/fushi.htm?catId=4&tagId=11244","text":"手提包"},{"id":"185910","level":"0","tag":"","targetUrl":"https://guang.taobao.com/street/fushi.htm?catId=4&tagId=11232","text":"邮差包"},{"id":"185911","level":"0","tag":"","targetUrl":"https://guang.taobao.com/street/fushi.htm?catId=4&tagId=11233","text":"铆钉包"},{"id":"185912","level":"0","tag":"","targetUrl":"https://guang.taobao.com/street/fushi.htm?catId=4&tagId=11934","text":"果冻包"},{"id":"185913","level":"0","tag":"","targetUrl":"https://guang.taobao.com/street/fushi.htm?catId=4&tagId=11935","text":"信封包"},{"id":"185914","level":"0","tag":"","targetUrl":"https://guang.taobao.com/street/fushi.htm?catId=4&tagId=11936","text":"复古包"},{"id":"185915","level":"0","tag":"","targetUrl":"https://guang.taobao.com/street/fushi.htm?catId=4&tagId=11937","text":"水桶包"},{"id":"185916","level":"0","tag":"","targetUrl":"https://guang.taobao.com/street/fushi.htm?catId=4&tagId=12169","text":"机车包"},{"id":"185917","level":"0","tag":"","targetUrl":"https://guang.taobao.com/street/fushi.htm?catId=4&tagId=11694","text":"草编包"},{"id":"185918","level":"0","tag":"","targetUrl":"https://guang.taobao.com/street/fushi.htm?catId=4&tagId=11881","text":"笑脸包"},{"id":"185919","level":"0","tag":"","targetUrl":"https://guang.taobao.com/street/fushi.htm?catId=4&tagId=11942","text":"链条包"},{"id":"185920","level":"0","tag":"","targetUrl":"https://guang.taobao.com/street/fushi.htm?catId=4&tagId=11947","text":"流苏包"},{"id":"185921","level":"0","tag":"","targetUrl":"https://guang.taobao.com/street/fushi.htm?catId=4&tagId=11940","text":"花朵包"},{"id":"185922","level":"0","tag":"","targetUrl":"https://guang.taobao.com/street/fushi.htm?catId=5&tagId=11840","text":"毛衣链"},{"id":"185923","level":"0","tag":"","targetUrl":"https://guang.taobao.com/street/fushi.htm?catId=5&tagId=11674","text":"项链"},{"id":"185924","level":"0","tag":"","targetUrl":"https://guang.taobao.com/street/fushi.htm?catId=5&tagId=11676","text":"手链"},{"id":"185925","level":"0","tag":"","targetUrl":"https://guang.taobao.com/street/fushi.htm?catId=5&tagId=11677","text":"戒指"},{"id":"185926","level":"0","tag":"","targetUrl":"https://guang.taobao.com/street/fushi.htm?catId=5&tagId=11678","text":"耳环"},{"id":"185927","level":"0","tag":"","targetUrl":"https://guang.taobao.com/street/fushi.htm?catId=5&tagId=11679","text":"发饰"},{"id":"185928","level":"0","tag":"","targetUrl":"https://guang.taobao.com/street/fushi.htm?catId=5&tagId=11778","text":"手镯"},{"id":"185929","level":"0","tag":"","targetUrl":"https://guang.taobao.com/street/fushi.htm?catId=5&tagId=11670","text":"帽子"},{"id":"185930","level":"0","tag":"","targetUrl":"https://guang.taobao.com/street/fushi.htm?catId=5&tagId=11893","text":"围巾"},{"id":"185931","level":"0","tag":"","targetUrl":"https://guang.taobao.com/street/fushi.htm?catId=5&tagId=11919","text":"手套"},{"id":"185932","level":"0","tag":"","targetUrl":"https://guang.taobao.com/street/meizhuang.htm?catId=7&tagId=11348","text":"唇妆"},{"id":"185933","level":"0","tag":"","targetUrl":"https://guang.taobao.com/street/meizhuang.htm?catId=7&tagId=11629","text":"祛黑头"},{"id":"185934","level":"0","tag":"","targetUrl":"https://guang.taobao.com/street/meizhuang.htm?catId=7&tagId=11354","text":"画眼线"},{"id":"185935","level":"0","tag":"","targetUrl":"https://guang.taobao.com/street/meizhuang.htm?catId=7&tagId=11835","text":"画眉毛"},{"id":"185936","level":"0","tag":"","targetUrl":"https://guang.taobao.com/street/meizhuang.htm?catId=7&tagId=11732","text":"减龄妆"},{"id":"185937","level":"0","tag":"","targetUrl":"https://guang.taobao.com/street/meizhuang.htm?catId=7&tagId=11900","text":"职业妆"},{"id":"185938","level":"0","tag":"","targetUrl":"https://guang.taobao.com/street/meizhuang.htm?catId=7&tagId=11901","text":"约会妆"},{"id":"185939","level":"0","tag":"","targetUrl":"https://guang.taobao.com/street/meizhuang.htm?catId=7&tagId=11902","text":"瘦脸妆"},{"id":"185940","level":"0","tag":"","targetUrl":"https://guang.taobao.com/street/meizhuang.htm?catId=7&tagId=12173","text":"裸妆"},{"id":"185941","level":"0","tag":"","targetUrl":"https://guang.taobao.com/street/meizhuang.htm?catId=7&tagId=12301","text":"韩式妆容"},{"id":"185942","level":"0","tag":"","targetUrl":"https://guang.taobao.com/street/meizhuang.htm?catId=7&tagId=12196","text":"明星妆"},{"id":"185943","level":"0","tag":"","targetUrl":"https://guang.taobao.com/street/meizhuang.htm?catId=7&tagId=12362","text":"防晒"},{"id":"185944","level":"0","tag":"","targetUrl":"https://guang.taobao.com/street/meizhuang.htm?catId=7&tagId=11487","text":"美白"},{"id":"185945","level":"0","tag":"","targetUrl":"https://guang.taobao.com/street/meizhuang.htm?catId=7&tagId=11899","text":"去黑眼圈"},{"id":"185946","level":"0","tag":"","targetUrl":"https://guang.taobao.com/street/meizhuang.htm?catId=7&tagId=11729","text":"去痘痘"},{"id":"185947","level":"0","tag":"","targetUrl":"https://guang.taobao.com/street/meizhuang.htm?catId=7&tagId=11493","text":"缩毛孔"},{"id":"185948","level":"0","tag":"","targetUrl":"https://guang.taobao.com/street/meizhuang.htm?catId=7&tagId=11897","text":"去角质"},{"id":"185949","level":"0","tag":"","targetUrl":"https://guang.taobao.com/street/meizhuang.htm?catId=7&tagId=11653","text":"卸妆"},{"id":"185950","level":"0","tag":"","targetUrl":"https://guang.taobao.com/street/meizhuang.htm?catId=21&tagId=11328","text":"马尾辫"},{"id":"185951","level":"0","tag":"","targetUrl":"https://guang.taobao.com/street/meizhuang.htm?catId=21&tagId=11331","text":"丸子头"},{"id":"185952","level":"0","tag":"","targetUrl":"https://guang.taobao.com/street/meizhuang.htm?catId=21&tagId=11334","text":"DIY盘发"},{"id":"185953","level":"0","tag":"","targetUrl":"https://guang.taobao.com/street/meizhuang.htm?catId=21&tagId=11336","text":"DIY编发"},{"id":"185954","level":"0","tag":"","targetUrl":"https://guang.taobao.com/street/meizhuang.htm?catId=21&tagId=11725","text":"60秒扎发"},{"id":"185955","level":"0","tag":"","targetUrl":"https://guang.taobao.com/street/meizhuang.htm?catId=21&tagId=11743","text":"短发编发"},{"id":"185956","level":"0","tag":"","targetUrl":"https://guang.taobao.com/street/meizhuang.htm?catId=21&tagId=11328","text":"鱼骨辫"},{"id":"185957","level":"0","tag":"","targetUrl":"https://guang.taobao.com/street/meizhuang.htm?catId=21&tagId=11347","text":"刘海"},{"id":"185958","level":"0","tag":"","targetUrl":"https://guang.taobao.com/street/meizhuang.htm?catId=21&tagId=11710","text":"梨花头"},{"id":"185959","level":"0","tag":"","targetUrl":"https://guang.taobao.com/street/meizhuang.htm?catId=21&tagId=11712","text":"波波头"},{"id":"185960","level":"0","tag":"","targetUrl":"https://guang.taobao.com/street/meizhuang.htm?catId=21&tagId=11557","text":"护发心得"},{"id":"185961","level":"0","tag":"","targetUrl":"https://guang.taobao.com/street/jiaju.htm?catId=6&tagId=11568","text":"卧室"},{"id":"185962","level":"0","tag":"","targetUrl":"https://guang.taobao.com/street/jiaju.htm?catId=6&tagId=11501","text":"客厅"},{"id":"185963","level":"0","tag":"","targetUrl":"https://guang.taobao.com/street/jiaju.htm?catId=6&tagId=11569","text":"书房"},{"id":"185964","level":"0","tag":"","targetUrl":"https://guang.taobao.com/street/jiaju.htm?catId=6&tagId=11570","text":"厨房"},{"id":"185965","level":"0","tag":"","targetUrl":"https://guang.taobao.com/street/jiaju.htm?catId=6&tagId=11571","text":"餐厅"},{"id":"185966","level":"0","tag":"","targetUrl":"https://guang.taobao.com/street/jiaju.htm?catId=6&tagId=11572","text":"儿童房"},{"id":"185967","level":"0","tag":"","targetUrl":"https://guang.taobao.com/street/jiaju.htm?catId=6&tagId=11573","text":"阳台"},{"id":"185968","level":"0","tag":"","targetUrl":"https://guang.taobao.com/street/jiaju.htm?catId=6&tagId=11575","text":"飘窗"},{"id":"185969","level":"0","tag":"","targetUrl":"https://guang.taobao.com/street/jiaju.htm?catId=6&tagId=11576","text":"花园"},{"id":"185970","level":"0","tag":"","targetUrl":"https://guang.taobao.com/street/jiaju.htm?catId=6&tagId=11577","text":"阁楼"},{"id":"185971","level":"0","tag":"","targetUrl":"https://guang.taobao.com/street/jiaju.htm?catId=6&tagId=11578","text":"卫浴"},{"id":"185972","level":"0","tag":"","targetUrl":"https://guang.taobao.com/street/jiaju.htm?catId=6&tagId=11579","text":"衣帽间"},{"id":"185973","level":"0","tag":"","targetUrl":"https://guang.taobao.com/street/jiaju.htm?catId=6&tagId=11585","text":"简约"},{"id":"185974","level":"0","tag":"","targetUrl":"https://guang.taobao.com/street/jiaju.htm?catId=6&tagId=11586","text":"现代"},{"id":"185975","level":"0","tag":"","targetUrl":"https://guang.taobao.com/street/jiaju.htm?catId=6&tagId=11587","text":"欧式"},{"id":"185976","level":"0","tag":"","targetUrl":"https://guang.taobao.com/street/jiaju.htm?catId=6&tagId=11588","text":"田园"},{"id":"185977","level":"0","tag":"","targetUrl":"https://guang.taobao.com/street/jiaju.htm?catId=6&tagId=11589","text":"美式"},{"id":"185978","level":"0","tag":"","targetUrl":"https://guang.taobao.com/street/jiaju.htm?catId=6&tagId=11590","text":"中式"},{"id":"185979","level":"0","tag":"","targetUrl":"https://guang.taobao.com/street/jiaju.htm?catId=6&tagId=11591","text":"北欧"},{"id":"185980","level":"0","tag":"","targetUrl":"https://guang.taobao.com/street/jiaju.htm?catId=6&tagId=11592","text":"宜家"},{"id":"185981","level":"0","tag":"","targetUrl":"https://guang.taobao.com/street/jiaju.htm?catId=6&tagId=11593","text":"地中海"},{"id":"185982","level":"0","tag":"","targetUrl":"https://guang.taobao.com/street/jiaju.htm?catId=6&tagId=12445","text":"床品套件"},{"id":"185983","level":"0","tag":"","targetUrl":"https://guang.taobao.com/street/jiaju.htm?catId=6&tagId=12446","text":"毛毯"},{"id":"185984","level":"0","tag":"","targetUrl":"https://guang.taobao.com/street/jiaju.htm?catId=6&tagId=12452","text":"地垫"},{"id":"185985","level":"0","tag":"","targetUrl":"https://guang.taobao.com/street/jiaju.htm?catId=6&tagId=12453","text":"沙发垫"},{"id":"185986","level":"0","tag":"","targetUrl":"https://guang.taobao.com/street/jiaju.htm?catId=6&tagId=12454","text":"窗帘"},{"id":"185987","level":"0","tag":"","targetUrl":"https://guang.taobao.com/street/jiaju.htm?catId=6&tagId=12429","text":"床"},{"id":"185988","level":"0","tag":"","targetUrl":"https://guang.taobao.com/street/jiaju.htm?catId=6&tagId=12431","text":"椅子"},{"id":"185989","level":"0","tag":"","targetUrl":"https://guang.taobao.com/street/jiaju.htm?catId=6&tagId=12432","text":"凳子"},{"id":"185990","level":"0","tag":"","targetUrl":"https://guang.taobao.com/street/jiaju.htm?catId=6&tagId=12433","text":"茶几"},{"id":"185991","level":"0","tag":"","targetUrl":"https://guang.taobao.com/street/jiaju.htm?catId=6&tagId=12434","text":"书柜"},{"id":"185992","level":"0","tag":"","targetUrl":"https://guang.taobao.com/street/jiaju.htm?catId=6&tagId=12435","text":"衣柜"},{"id":"185993","level":"0","tag":"","targetUrl":"https://guang.taobao.com/street/jiaju.htm?catId=6&tagId=12436","text":"置物柜"},{"id":"185994","level":"0","tag":"","targetUrl":"https://guang.taobao.com/street/jiaju.htm?catId=6&tagId=12437","text":"置物架"},{"id":"185995","level":"0","tag":"","targetUrl":"https://guang.taobao.com/street/jiaju.htm?catId=6&tagId=12438","text":"衣帽架"},{"id":"185996","level":"0","tag":"","targetUrl":"https://guang.taobao.com/street/jiaju.htm?catId=6&tagId=12439","text":"花架"},{"id":"185997","level":"0","tag":"","targetUrl":"https://guang.taobao.com/street/jiaju.htm?catId=6&tagId=12440","text":"吧台"},{"id":"185998","level":"0","tag":"","targetUrl":"https://guang.taobao.com/street/jiaju.htm?catId=6&tagId=12441","text":"书桌"},{"id":"185999","level":"0","tag":"","targetUrl":"https://guang.taobao.com/street/jiaju.htm?catId=6&tagId=12442","text":"梳妆台"},{"id":"186000","level":"0","tag":"","targetUrl":"https://guang.taobao.com/street/jiaju.htm?catId=6&tagId=12443","text":"餐桌"},{"id":"186001","level":"0","tag":"","targetUrl":"https://guang.taobao.com/street/jiaju.htm?catId=6&tagId=12457","text":"创意饰品"},{"id":"186002","level":"0","tag":"","targetUrl":"https://guang.taobao.com/street/jiaju.htm?catId=6&tagId=12458","text":"钟"},{"id":"186003","level":"0","tag":"","targetUrl":"https://guang.taobao.com/street/jiaju.htm?catId=6&tagId=12459","text":"照片墙"},{"id":"186004","level":"0","tag":"","targetUrl":"https://guang.taobao.com/street/jiaju.htm?catId=6&tagId=12460","text":"花瓶"},{"id":"186005","level":"0","tag":"","targetUrl":"https://guang.taobao.com/street/jiaju.htm?catId=6&tagId=12462","text":"烛台"},{"id":"186006","level":"0","tag":"","targetUrl":"https://guang.taobao.com/street/jiaju.htm?catId=6&tagId=12463","text":"储物罐"},{"id":"186007","level":"0","tag":"","targetUrl":"https://guang.taobao.com/street/jiaju.htm?catId=6&tagId=12465","text":"摆件"},{"id":"186008","level":"0","tag":"","targetUrl":"https://guang.taobao.com/street/jiaju.htm?catId=6&tagId=12466","text":"风铃"},{"id":"186009","level":"0","tag":"","targetUrl":"https://guang.taobao.com/street/jiaju.htm?catId=6&tagId=12467","text":"装饰画"},{"id":"186010","level":"0","tag":"","targetUrl":"https://guang.taobao.com/street/jiaju.htm?catId=6&tagId=12468","text":"墙贴"},{"id":"186011","level":"0","tag":"","targetUrl":"https://guang.taobao.com/street/jiaju.htm?catId=6&tagId=12469","text":"永生花"},{"id":"186012","level":"0","tag":"","targetUrl":"https://guang.taobao.com/street/jiaju.htm?catId=6&tagId=12402","text":"创意家居"},{"id":"186013","level":"0","tag":"","targetUrl":"https://guang.taobao.com/street/jiaju.htm?catId=6&tagId=12403","text":"mini电扇"},{"id":"186014","level":"0","tag":"","targetUrl":"https://guang.taobao.com/street/jiaju.htm?catId=6&tagId=12417","text":"办公桌绿植"},{"id":"186015","level":"0","tag":"","targetUrl":"https://guang.taobao.com/street/jiaju.htm?catId=6&tagId=12405","text":"贴纸"},{"id":"186016","level":"0","tag":"","targetUrl":"https://guang.taobao.com/street/jiaju.htm?catId=6&tagId=12406","text":"伞"},{"id":"186017","level":"0","tag":"","targetUrl":"https://guang.taobao.com/street/jiaju.htm?catId=6&tagId=12423","text":"收纳"},{"id":"186018","level":"0","tag":"","targetUrl":"https://guang.taobao.com/street/jiaju.htm?catId=6&tagId=12404","text":"招财猫"}],"item":[{"bizType":"item1","enablePersonal":"y","id":"161314","imgUrl":"//gtms03.alicdn.com/tps/i3/TB1ta2ULVXXXXc.XXXXj64lTXXX-200-200.jpg","level":"0","targetUrl":"https://guang.taobao.com/street/fushi.htm?spm=a310p.7395723_1.1998038892.2.oXJK8m&catId=1","text1":"春季新款","text2":""},{"bizType":"item1","enablePersonal":"y","id":"161315","imgUrl":"//gtms02.alicdn.com/tps/i2/TB1nKzPLVXXXXcdXpXXj64lTXXX-200-200.jpg","level":"0","targetUrl":"https://guang.taobao.com/street/fushi.htm?spm=a310p.7395723_1.1998038892.9.9GSPtX&catId=3","text1":"唯美女鞋","text2":""},{"bizType":"item2","enablePersonal":"y","id":"161316","imgUrl":"//gtms01.alicdn.com/tps/i1/TB15J6NLVXXXXXlXFXXj64lTXXX-200-200.jpg","level":"0","targetUrl":"https://guang.taobao.com/street/fushi.htm?spm=a310p.7395723_3.1998038892.16.LqhLqB&catId=4","text1":"“包包”","text2":"能治百病"},{"bizType":"item2","enablePersonal":"y","id":"161317","imgUrl":"//gtms03.alicdn.com/tps/i3/TB1WB6ILVXXXXb7XFXXj64lTXXX-200-200.jpg","level":"0","targetUrl":"https://guang.taobao.com/street/jiaju.htm?spm=a310p.7395723_4.1998042884.5.THOvfM","text1":"创意家居","text2":"温馨小家"}],"news":[{"bizType":"news1","id":"185784","imgUrl":"//img.alicdn.com/tfs/TB1t9v9RFXXXXaCXXXXXXXXXXXX-360-280.jpg","level":"0","targetUrl":"https://guang.taobao.com/activity/channel.htm?id=714","text1":"潮搭","text2":"内衣外穿超减龄","text3":""}],"totalinfo":[{"bizCode":"aiguangjie","bizName":"爱逛街","id":"6028","imgUrl":"//gw.alicdn.com/tps/TB1JTeNMXXXXXb.XXXXXXXXXXXX-200-200.png","level":"0","logoBackgroundColor":"#fe6fa6","name":"爱逛街","productId":"1002","scm":"","targetUrl":"https://guang.taobao.com/","templateId":"t1","textBackgroundColor":"#fe6fa6","topOrder":"","userId":"0"}]}],"success":true,"version":"1.055"}},"success":true,"version":"1.01"}